{"absolute_quantity": null, "file_links": [], "labels": [], "mass_fraction": null, "material": {"id": "cea1eaef-19ac-4d34-98e1-bda2ad43868d", "scope": "auto", "type": "link_by_uid"}, "name": "Sample", "notes": null, "number_fraction": null, "process": {"id": "5346a68e-e6cc-43f3-ad0e-55c496e2bd0b", "scope": "auto", "type": "link_by_uid"}, "spec": {"id": "41dc1199-4e6b-495f-8a7d-deaf3d78d3b9", "scope": "auto", "type": "link_by_uid"}, "tags": [], "type": "ingredient_run", "uids": {"auto": "17b8b73a-2b3f-48ba-b8f7-f9f689dea527"}, "volume_fraction": null}