{"absolute_quantity": null, "file_links": [], "labels": [], "mass_fraction": null, "material": {"id": "e32cfed9-df5d-4a8f-b259-a7479bae7ab1", "scope": "auto", "type": "link_by_uid"}, "name": "Flyer and Spacer", "notes": null, "number_fraction": null, "process": {"id": "3443d950-a527-49b6-91f6-811020d85558", "scope": "auto", "type": "link_by_uid"}, "spec": {"id": "87009246-2374-4c45-b571-49174db7f291", "scope": "auto", "type": "link_by_uid"}, "tags": [], "type": "ingredient_run", "uids": {"auto": "50381d60-fa42-4328-a962-ff260eb6cf5b"}, "volume_fraction": null}