{"absolute_quantity": null, "file_links": [], "labels": [], "mass_fraction": null, "material": {"id": "ee45db01-51db-43e8-b606-c7108815b50a", "scope": "auto", "type": "link_by_uid"}, "name": "Flyer Stack", "notes": null, "number_fraction": null, "process": {"id": "b35f5fba-ef57-4b80-94f4-a4a42b465082", "scope": "auto", "type": "link_by_uid"}, "spec": {"id": "99bc9f4f-ccb3-4aad-b28d-18a367350dbf", "scope": "auto", "type": "link_by_uid"}, "tags": [], "type": "ingredient_run", "uids": {"auto": "8e6aabc7-1c0a-4ef5-8b48-dcbb9ba1d9cc"}, "volume_fraction": null}