{"absolute_quantity": null, "file_links": [], "labels": [], "mass_fraction": null, "material": {"id": "2f96b77e-7096-44cb-b2e1-bc194d717d35", "scope": "auto", "type": "link_by_uid"}, "name": "Sample", "notes": null, "number_fraction": null, "process": {"id": "f6e9cbbe-c263-4025-b101-8b87e9c59c38", "scope": "auto", "type": "link_by_uid"}, "spec": {"id": "2cbd9ad7-3dcb-4708-bffc-c0ffe42c04f5", "scope": "auto", "type": "link_by_uid"}, "tags": [], "type": "ingredient_run", "uids": {"auto": "dbb6eac8-cfcc-4ba1-b834-9941bedfeeba"}, "volume_fraction": null}