{"absolute_quantity": null, "file_links": [], "labels": [], "mass_fraction": null, "material": {"id": "effbb7b6-657f-408c-a9db-46465b200734", "scope": "auto", "type": "link_by_uid"}, "name": "Chosen Flyer", "notes": null, "number_fraction": null, "process": {"id": "6e749c5b-47a3-41bf-9957-2e1fc6d30dfc", "scope": "auto", "type": "link_by_uid"}, "spec": {"id": "0ded66f7-777a-4713-a70d-16e08af53266", "scope": "auto", "type": "link_by_uid"}, "tags": [], "type": "ingredient_run", "uids": {"auto": "7a56717c-097e-4515-bb6c-f6898d13753c"}, "volume_fraction": null}