{"absolute_quantity": null, "file_links": [], "labels": [], "mass_fraction": null, "material": {"id": "215634ec-f01b-4af8-9197-bcfd0a255d64", "scope": "auto", "type": "link_by_uid"}, "name": "Flyer Stack", "notes": null, "number_fraction": null, "process": {"id": "dd4d18a8-ac9f-4103-9e89-eb0a8b6aad00", "scope": "auto", "type": "link_by_uid"}, "spec": {"id": "95b6f6c6-3520-4685-858a-786c330fdd55", "scope": "auto", "type": "link_by_uid"}, "tags": [], "type": "ingredient_run", "uids": {"auto": "8f4a1e73-6d12-4e09-ab75-2d0b3cc7a6a1"}, "volume_fraction": null}