{"absolute_quantity": null, "file_links": [], "labels": [], "mass_fraction": null, "material": {"id": "da337a78-38cc-488d-9300-3d860ad1e5c8", "scope": "auto", "type": "link_by_uid"}, "name": "Flyer Stack", "notes": null, "number_fraction": null, "process": {"id": "99ccdda8-9e83-4ed2-b811-3ae0a966619c", "scope": "auto", "type": "link_by_uid"}, "spec": {"id": "29d6d3dd-a896-42b2-9382-572778986867", "scope": "auto", "type": "link_by_uid"}, "tags": [], "type": "ingredient_run", "uids": {"auto": "63e58fd4-0ca2-4410-a1f7-1d0b7dde5790"}, "volume_fraction": null}