{"absolute_quantity": null, "file_links": [], "labels": [], "mass_fraction": null, "material": {"id": "088a35f5-e52c-4c4a-8c69-4feb79e7fcec", "scope": "auto", "type": "link_by_uid"}, "name": "Cut Spacer", "notes": null, "number_fraction": null, "process": {"id": "d3e6f4e5-a11f-45ff-a2b6-447de47c7a4c", "scope": "auto", "type": "link_by_uid"}, "spec": {"id": "21483510-58eb-4db4-9d68-e93f953a788f", "scope": "auto", "type": "link_by_uid"}, "tags": [], "type": "ingredient_run", "uids": {"auto": "cc212ffa-0b19-4b65-ba53-76acd4089fb8"}, "volume_fraction": null}