{"absolute_quantity": null, "file_links": [], "labels": [], "mass_fraction": null, "material": {"id": "254a0f64-0ad6-4866-8340-e538bed71d1f", "scope": "auto", "type": "link_by_uid"}, "name": "Impact Sample", "notes": null, "number_fraction": null, "process": {"id": "a57ddd48-8c50-406c-b67b-f472bfc34b31", "scope": "auto", "type": "link_by_uid"}, "spec": {"id": "49ad6439-50c6-47ae-a107-2f48a595707c", "scope": "auto", "type": "link_by_uid"}, "tags": [], "type": "ingredient_run", "uids": {"auto": "8995bd8a-1931-4f15-ae1c-4c8698f5740c"}, "volume_fraction": null}