{"absolute_quantity": null, "file_links": [], "labels": [], "mass_fraction": null, "material": {"id": "d45fbe2a-87f6-4e0e-8fd6-dbe57b8e16fe", "scope": "auto", "type": "link_by_uid"}, "name": "Flyer Stack", "notes": null, "number_fraction": null, "process": {"id": "e1f6cd08-5048-45bf-9303-1a442170be98", "scope": "auto", "type": "link_by_uid"}, "spec": {"id": "29d6d3dd-a896-42b2-9382-572778986867", "scope": "auto", "type": "link_by_uid"}, "tags": [], "type": "ingredient_run", "uids": {"auto": "ae3767b4-bc82-4f8f-967f-e55b6c9b9fde"}, "volume_fraction": null}