{"absolute_quantity": null, "file_links": [], "labels": [], "mass_fraction": null, "material": {"id": "5805cad2-fab2-4263-b63c-3dc9867b2efd", "scope": "auto", "type": "link_by_uid"}, "name": "Spacer Material", "notes": null, "number_fraction": null, "process": {"id": "0850a430-3ef7-4205-9822-10fbf8533eae", "scope": "auto", "type": "link_by_uid"}, "spec": {"id": "a8af187a-7c55-46f5-80b5-9556c8721331", "scope": "auto", "type": "link_by_uid"}, "tags": [], "type": "ingredient_run", "uids": {"auto": "cc5b8da2-1a96-4912-9551-76dee0cde4d1"}, "volume_fraction": null}