{"absolute_quantity": null, "file_links": [], "labels": [], "mass_fraction": null, "material": {"id": "52e989e0-a389-4183-8143-38488edb81cb", "scope": "auto", "type": "link_by_uid"}, "name": "Spacer Material", "notes": null, "number_fraction": null, "process": {"id": "710b96dc-d711-47aa-8c4c-5b88015c51aa", "scope": "auto", "type": "link_by_uid"}, "spec": {"id": "d04ca5d5-15e7-417f-b8d7-34eabd413dc5", "scope": "auto", "type": "link_by_uid"}, "tags": [], "type": "ingredient_run", "uids": {"auto": "94aa1814-d0ea-42b4-bdc3-543d13d52106"}, "volume_fraction": null}