{"absolute_quantity": null, "file_links": [], "labels": [], "mass_fraction": null, "material": {"id": "9c94feb7-f562-4c98-84f0-510732e52e0f", "scope": "auto", "type": "link_by_uid"}, "name": "Spacer Material", "notes": null, "number_fraction": null, "process": {"id": "e13bf4e1-5a07-4042-b45a-31b5c7ed114f", "scope": "auto", "type": "link_by_uid"}, "spec": {"id": "a6aeb3e4-f2cc-4d36-a3f9-82262f43a9f3", "scope": "auto", "type": "link_by_uid"}, "tags": [], "type": "ingredient_run", "uids": {"auto": "4275446b-6d39-4b36-8e04-fcf6b54052dd"}, "volume_fraction": null}