{"absolute_quantity": null, "file_links": [], "labels": [], "mass_fraction": null, "material": {"id": "bc916e77-b809-49e1-9231-124337c4bafe", "scope": "auto", "type": "link_by_uid"}, "name": "Impact Sample", "notes": null, "number_fraction": null, "process": {"id": "2c039246-d5dd-4e00-84df-dc9f94267c71", "scope": "auto", "type": "link_by_uid"}, "spec": {"id": "1e9aea5f-ac79-44b9-b518-971bd7472e1b", "scope": "auto", "type": "link_by_uid"}, "tags": [], "type": "ingredient_run", "uids": {"auto": "2cc04ee5-052a-487d-9bb1-82ea8e78c6bc"}, "volume_fraction": null}