{"absolute_quantity": null, "file_links": [], "labels": [], "mass_fraction": null, "material": {"id": "f13abb76-c5eb-43ed-926d-97395fa49069", "scope": "auto", "type": "link_by_uid"}, "name": "Cut Spacer", "notes": null, "number_fraction": null, "process": {"id": "e1ef7ad5-c5be-4ff1-bdf6-8a64af0b46a2", "scope": "auto", "type": "link_by_uid"}, "spec": {"id": "de0f7578-03f8-4085-a190-1f180ff5ca3a", "scope": "auto", "type": "link_by_uid"}, "tags": [], "type": "ingredient_run", "uids": {"auto": "56681d95-f839-4655-99b4-c92125fa8fb4"}, "volume_fraction": null}