{"absolute_quantity": null, "file_links": [], "labels": [], "mass_fraction": null, "material": {"id": "fccabb58-dc1e-4a9a-907f-23d8462eba7d", "scope": "auto", "type": "link_by_uid"}, "name": "Sample", "notes": null, "number_fraction": null, "process": {"id": "d071a446-43e4-4777-bbdf-f5baa995a9ca", "scope": "auto", "type": "link_by_uid"}, "spec": {"id": "0477e154-3677-4773-9bed-e8e9e8ac8385", "scope": "auto", "type": "link_by_uid"}, "tags": [], "type": "ingredient_run", "uids": {"auto": "fcea1129-22fa-446a-95f1-00d79cf1cda7"}, "volume_fraction": null}