{"absolute_quantity": null, "file_links": [], "labels": [], "mass_fraction": null, "material": {"id": "e117793b-36eb-4d5e-a807-a75b0e32310d", "scope": "auto", "type": "link_by_uid"}, "name": "Spacer Material", "notes": null, "number_fraction": null, "process": {"id": "09dc2053-a6ef-4ecc-9c8f-370bf7cff714", "scope": "auto", "type": "link_by_uid"}, "spec": {"id": "d04ca5d5-15e7-417f-b8d7-34eabd413dc5", "scope": "auto", "type": "link_by_uid"}, "tags": [], "type": "ingredient_run", "uids": {"auto": "57fda207-dc42-4e79-a357-8bdbe0baa91a"}, "volume_fraction": null}