{"absolute_quantity": null, "file_links": [], "labels": [], "mass_fraction": null, "material": {"id": "31d55d6e-c3b0-479d-9ce6-e2d06cc6810b", "scope": "auto", "type": "link_by_uid"}, "name": "Flyer and Spacer", "notes": null, "number_fraction": null, "process": {"id": "3720dd73-89dd-4bae-bf89-94aac7a9fb79", "scope": "auto", "type": "link_by_uid"}, "spec": {"id": "b8875f80-cc5d-414c-a6f3-17cd3645483c", "scope": "auto", "type": "link_by_uid"}, "tags": [], "type": "ingredient_run", "uids": {"auto": "3c49d8eb-f4bf-431d-adec-10e9011622e9"}, "volume_fraction": null}