{"absolute_quantity": null, "file_links": [], "labels": [], "mass_fraction": null, "material": {"id": "7a40bbcc-d450-4ca6-bfbc-fffe8fbec589", "scope": "auto", "type": "link_by_uid"}, "name": "Flyer and Spacer", "notes": null, "number_fraction": null, "process": {"id": "0140c952-406f-481d-b1cb-01a0781f5325", "scope": "auto", "type": "link_by_uid"}, "spec": {"id": "87009246-2374-4c45-b571-49174db7f291", "scope": "auto", "type": "link_by_uid"}, "tags": [], "type": "ingredient_run", "uids": {"auto": "8982223a-2605-458a-88b0-d3ea5682a7cc"}, "volume_fraction": null}