{"absolute_quantity": null, "file_links": [], "labels": [], "mass_fraction": null, "material": {"id": "d66d3e73-253a-4c1b-8df1-526e2eeca8f9", "scope": "auto", "type": "link_by_uid"}, "name": "Flyer and Spacer", "notes": null, "number_fraction": null, "process": {"id": "2911f6c7-02fa-492a-b988-87b1e421bbb0", "scope": "auto", "type": "link_by_uid"}, "spec": {"id": "760d64f2-2eb8-4d85-8423-031ff309af59", "scope": "auto", "type": "link_by_uid"}, "tags": [], "type": "ingredient_run", "uids": {"auto": "66c2fe35-31b1-40fd-8683-f5a4ae30bb66"}, "volume_fraction": null}