{"absolute_quantity": null, "file_links": [], "labels": [], "mass_fraction": null, "material": {"id": "dee3605d-82e8-4ce5-b684-62fb3d868b5a", "scope": "auto", "type": "link_by_uid"}, "name": "Sample", "notes": null, "number_fraction": null, "process": {"id": "f545d387-cfdb-4a95-9cb9-416212b2fc12", "scope": "auto", "type": "link_by_uid"}, "spec": {"id": "e2d1601a-34b8-4fed-9ff8-af13e0de8d00", "scope": "auto", "type": "link_by_uid"}, "tags": [], "type": "ingredient_run", "uids": {"auto": "7ab94f64-91cb-41d6-b1e3-9ade5f04daea"}, "volume_fraction": null}