{"absolute_quantity": null, "file_links": [], "labels": [], "mass_fraction": null, "material": {"id": "ca79fb52-7727-460e-ae6e-cf99d52f007f", "scope": "auto", "type": "link_by_uid"}, "name": "Flyer Stack", "notes": null, "number_fraction": null, "process": {"id": "67cd612d-26f8-4dec-be9d-c1dcaeb71b89", "scope": "auto", "type": "link_by_uid"}, "spec": {"id": "95b6f6c6-3520-4685-858a-786c330fdd55", "scope": "auto", "type": "link_by_uid"}, "tags": [], "type": "ingredient_run", "uids": {"auto": "778e4e1f-5361-426d-a696-74ffa6a478cd"}, "volume_fraction": null}