{"absolute_quantity": null, "file_links": [], "labels": [], "mass_fraction": null, "material": {"id": "cac08e6e-b032-47fa-8f43-d223a1186ed6", "scope": "auto", "type": "link_by_uid"}, "name": "Spacer Material", "notes": null, "number_fraction": null, "process": {"id": "a9d8fd4f-5480-46f7-a868-9340e82ddb2a", "scope": "auto", "type": "link_by_uid"}, "spec": {"id": "a6aeb3e4-f2cc-4d36-a3f9-82262f43a9f3", "scope": "auto", "type": "link_by_uid"}, "tags": [], "type": "ingredient_run", "uids": {"auto": "01bd0f9f-35a9-459e-af7a-1279fcc9aba5"}, "volume_fraction": null}