{"absolute_quantity": null, "file_links": [], "labels": [], "mass_fraction": null, "material": {"id": "64ae0bde-97e0-482a-a7f9-842fcf36081a", "scope": "auto", "type": "link_by_uid"}, "name": "Flyer Stack", "notes": null, "number_fraction": null, "process": {"id": "93f8b2c0-404b-4d0d-8099-2930f13a1915", "scope": "auto", "type": "link_by_uid"}, "spec": {"id": "29d6d3dd-a896-42b2-9382-572778986867", "scope": "auto", "type": "link_by_uid"}, "tags": [], "type": "ingredient_run", "uids": {"auto": "3ec2e9b3-d99b-442f-9e85-e77fe0a5dc0b"}, "volume_fraction": null}