{"absolute_quantity": null, "file_links": [], "labels": [], "mass_fraction": null, "material": {"id": "d2471ae6-f6fb-4c6c-9517-c11fe12ff056", "scope": "auto", "type": "link_by_uid"}, "name": "Spacer Material", "notes": null, "number_fraction": null, "process": {"id": "cb3c8a38-2b95-4e68-8079-d9fce0329722", "scope": "auto", "type": "link_by_uid"}, "spec": {"id": "d04ca5d5-15e7-417f-b8d7-34eabd413dc5", "scope": "auto", "type": "link_by_uid"}, "tags": [], "type": "ingredient_run", "uids": {"auto": "3aac216a-e479-4833-b60e-bfb57e7d6c55"}, "volume_fraction": null}