{"absolute_quantity": null, "file_links": [], "labels": [], "mass_fraction": null, "material": {"id": "f0127939-ff8a-43f8-9188-895d9ba20bac", "scope": "auto", "type": "link_by_uid"}, "name": "Flyer Stack", "notes": null, "number_fraction": null, "process": {"id": "500949b4-afa1-49d0-9916-f6dd2d673edd", "scope": "auto", "type": "link_by_uid"}, "spec": {"id": "4af28096-8458-4f04-b0c3-e8e336286945", "scope": "auto", "type": "link_by_uid"}, "tags": [], "type": "ingredient_run", "uids": {"auto": "de77daec-19d8-41d6-8765-339cc7d8b0aa"}, "volume_fraction": null}