{"absolute_quantity": null, "file_links": [], "labels": [], "mass_fraction": null, "material": {"id": "4da7b0b5-fd9b-4f0b-a45c-fd09f2768218", "scope": "auto", "type": "link_by_uid"}, "name": "Impact Sample", "notes": null, "number_fraction": null, "process": {"id": "80f0eae7-f348-4762-8a3f-63359dea6110", "scope": "auto", "type": "link_by_uid"}, "spec": {"id": "ea2988c8-27e0-4e79-8f26-28100a4d30a1", "scope": "auto", "type": "link_by_uid"}, "tags": [], "type": "ingredient_run", "uids": {"auto": "bd1f6373-9205-4b13-8f4c-7148142d5a03"}, "volume_fraction": null}