{"absolute_quantity": null, "file_links": [], "labels": [], "mass_fraction": null, "material": {"id": "b6d0309b-15a6-4baf-af94-ca1ab93d4ec5", "scope": "auto", "type": "link_by_uid"}, "name": "Flyer Stack", "notes": null, "number_fraction": null, "process": {"id": "6c17567c-6dda-41b7-876b-04574cc3c475", "scope": "auto", "type": "link_by_uid"}, "spec": {"id": "95b6f6c6-3520-4685-858a-786c330fdd55", "scope": "auto", "type": "link_by_uid"}, "tags": [], "type": "ingredient_run", "uids": {"auto": "25dfa3e5-e0ed-4497-ba3a-11aef32fa55b"}, "volume_fraction": null}