{"absolute_quantity": null, "file_links": [], "labels": [], "mass_fraction": null, "material": {"id": "19fa88cf-2b3f-41c0-b560-5bb6748d6390", "scope": "auto", "type": "link_by_uid"}, "name": "Chosen Flyer", "notes": null, "number_fraction": null, "process": {"id": "b1b65233-5717-4b5a-889c-355e3eb875f3", "scope": "auto", "type": "link_by_uid"}, "spec": {"id": "e6223eae-51d4-426c-b10b-1ab55849d4d3", "scope": "auto", "type": "link_by_uid"}, "tags": [], "type": "ingredient_run", "uids": {"auto": "1b7b4931-b1d4-49d0-a120-7fa0f1ed21a7"}, "volume_fraction": null}