{"absolute_quantity": null, "file_links": [], "labels": [], "mass_fraction": null, "material": {"id": "36160dce-f812-4d7f-b221-b159c13a540d", "scope": "auto", "type": "link_by_uid"}, "name": "Flyer and Spacer", "notes": null, "number_fraction": null, "process": {"id": "12dbcf40-12e9-4845-b4ae-85b34b84160a", "scope": "auto", "type": "link_by_uid"}, "spec": {"id": "e15f14a7-9603-4eab-8014-ccff5c11d536", "scope": "auto", "type": "link_by_uid"}, "tags": [], "type": "ingredient_run", "uids": {"auto": "fcba92c6-f7da-48ea-a826-2817c37bf2ce"}, "volume_fraction": null}