{"absolute_quantity": null, "file_links": [], "labels": [], "mass_fraction": null, "material": {"id": "836dc292-39d7-4d03-84e4-3add1e0c2c96", "scope": "auto", "type": "link_by_uid"}, "name": "Chosen Flyer", "notes": null, "number_fraction": null, "process": {"id": "9e58c278-dd4f-4a68-a810-02328f300b01", "scope": "auto", "type": "link_by_uid"}, "spec": {"id": "b6f0cf40-5e12-46a2-a5ac-0977a0419e00", "scope": "auto", "type": "link_by_uid"}, "tags": [], "type": "ingredient_run", "uids": {"auto": "7c87beb1-8d56-462b-9f29-2475c5f9b7c9"}, "volume_fraction": null}