{"absolute_quantity": null, "file_links": [], "labels": [], "mass_fraction": null, "material": {"id": "0eed2c76-2aa2-4174-ac94-e5ba9d192cd2", "scope": "auto", "type": "link_by_uid"}, "name": "Flyer and Spacer", "notes": null, "number_fraction": null, "process": {"id": "bd681084-ce9a-4b6e-a816-6982525d9356", "scope": "auto", "type": "link_by_uid"}, "spec": {"id": "b8875f80-cc5d-414c-a6f3-17cd3645483c", "scope": "auto", "type": "link_by_uid"}, "tags": [], "type": "ingredient_run", "uids": {"auto": "a8f044de-e32c-47bd-9677-19c4449bf184"}, "volume_fraction": null}