{"absolute_quantity": null, "file_links": [], "labels": [], "mass_fraction": null, "material": {"id": "2562d35b-4ffa-4f0e-9583-a8b5e9e20e40", "scope": "auto", "type": "link_by_uid"}, "name": "Chosen Flyer", "notes": null, "number_fraction": null, "process": {"id": "f0b56022-eeb9-4bbe-a79e-074db3243a9c", "scope": "auto", "type": "link_by_uid"}, "spec": {"id": "e6223eae-51d4-426c-b10b-1ab55849d4d3", "scope": "auto", "type": "link_by_uid"}, "tags": [], "type": "ingredient_run", "uids": {"auto": "7035d78a-ad7a-4033-a026-876f81d511bd"}, "volume_fraction": null}