{"absolute_quantity": null, "file_links": [], "labels": [], "mass_fraction": null, "material": {"id": "5f89ef6c-af73-4faa-8863-e5b6e64ed2ba", "scope": "auto", "type": "link_by_uid"}, "name": "Sample", "notes": null, "number_fraction": null, "process": {"id": "f6ffc15e-cbd9-46e1-9646-13e5966d74ed", "scope": "auto", "type": "link_by_uid"}, "spec": {"id": "1e9e07a3-4c1d-44bf-ae4f-32d6563aad5b", "scope": "auto", "type": "link_by_uid"}, "tags": [], "type": "ingredient_run", "uids": {"auto": "4d39e77c-c4ab-4a23-ad5e-1332346ff1f7"}, "volume_fraction": null}