{"absolute_quantity": null, "file_links": [], "labels": [], "mass_fraction": null, "material": {"id": "cf5698d4-3742-40cb-8d01-5bbcb3e530ce", "scope": "auto", "type": "link_by_uid"}, "name": "Flyer Stack", "notes": null, "number_fraction": null, "process": {"id": "0a6076d0-28fd-461a-965a-9f6e4704cc57", "scope": "auto", "type": "link_by_uid"}, "spec": {"id": "95b6f6c6-3520-4685-858a-786c330fdd55", "scope": "auto", "type": "link_by_uid"}, "tags": [], "type": "ingredient_run", "uids": {"auto": "ec10515f-396a-4348-b5e1-e85dd3ebdbc0"}, "volume_fraction": null}