{"absolute_quantity": null, "file_links": [], "labels": [], "mass_fraction": null, "material": {"id": "7a225aff-d338-4469-a23f-a6dd2422dcba", "scope": "auto", "type": "link_by_uid"}, "name": "Flyer and Spacer", "notes": null, "number_fraction": null, "process": {"id": "e027aeb4-b69f-46ed-940c-94cba7c0dd94", "scope": "auto", "type": "link_by_uid"}, "spec": {"id": "87009246-2374-4c45-b571-49174db7f291", "scope": "auto", "type": "link_by_uid"}, "tags": [], "type": "ingredient_run", "uids": {"auto": "1016bd4a-060a-4f6c-a1a7-bda3088b638f"}, "volume_fraction": null}