{"absolute_quantity": null, "file_links": [], "labels": [], "mass_fraction": null, "material": {"id": "21fe538e-f78f-47f3-accd-ffdc44faff23", "scope": "auto", "type": "link_by_uid"}, "name": "Flyer and Spacer", "notes": null, "number_fraction": null, "process": {"id": "54638652-1dd7-4d46-9a97-3e6efb9846c9", "scope": "auto", "type": "link_by_uid"}, "spec": {"id": "b8875f80-cc5d-414c-a6f3-17cd3645483c", "scope": "auto", "type": "link_by_uid"}, "tags": [], "type": "ingredient_run", "uids": {"auto": "c44f4ce7-0f83-4cd3-958f-357e19ad9b2f"}, "volume_fraction": null}