{"absolute_quantity": null, "file_links": [], "labels": [], "mass_fraction": null, "material": {"id": "03255431-406f-4604-956e-a493e5a5cfe6", "scope": "auto", "type": "link_by_uid"}, "name": "Cut Spacer", "notes": null, "number_fraction": null, "process": {"id": "862c9fad-e2b8-4fd7-851f-61704289aad3", "scope": "auto", "type": "link_by_uid"}, "spec": {"id": "21483510-58eb-4db4-9d68-e93f953a788f", "scope": "auto", "type": "link_by_uid"}, "tags": [], "type": "ingredient_run", "uids": {"auto": "1dfc677e-fbba-4bbd-8264-b242b773cb9e"}, "volume_fraction": null}