{"absolute_quantity": null, "file_links": [], "labels": [], "mass_fraction": null, "material": {"id": "582f5103-0ea7-40ea-908a-725b1efa7060", "scope": "auto", "type": "link_by_uid"}, "name": "Flyer Stack", "notes": null, "number_fraction": null, "process": {"id": "013f13b7-7b7d-45f9-bc0b-72ab023533fa", "scope": "auto", "type": "link_by_uid"}, "spec": {"id": "95b6f6c6-3520-4685-858a-786c330fdd55", "scope": "auto", "type": "link_by_uid"}, "tags": [], "type": "ingredient_run", "uids": {"auto": "3d77e779-462e-44ef-b0c9-9d236deceb99"}, "volume_fraction": null}