{"absolute_quantity": null, "file_links": [], "labels": [], "mass_fraction": null, "material": {"id": "139668a6-1830-4f97-8ad6-cb68aaaacc85", "scope": "auto", "type": "link_by_uid"}, "name": "Flyer Stack", "notes": null, "number_fraction": null, "process": {"id": "034d8b70-2fdd-4ed5-a9e8-2c8710d545b5", "scope": "auto", "type": "link_by_uid"}, "spec": {"id": "57184495-3921-406f-ad65-8e0ede1d4da1", "scope": "auto", "type": "link_by_uid"}, "tags": [], "type": "ingredient_run", "uids": {"auto": "c8892e93-313a-4429-952c-d2db5b176521"}, "volume_fraction": null}