{"absolute_quantity": null, "file_links": [], "labels": [], "mass_fraction": null, "material": {"id": "c47436b2-5ded-4e2a-bf29-c2b56fde8505", "scope": "auto", "type": "link_by_uid"}, "name": "Sample", "notes": null, "number_fraction": null, "process": {"id": "5cec004d-e69a-4d75-94e9-e96bae5604f6", "scope": "auto", "type": "link_by_uid"}, "spec": {"id": "10b6bb36-a623-4426-954b-68d7ac09062c", "scope": "auto", "type": "link_by_uid"}, "tags": [], "type": "ingredient_run", "uids": {"auto": "d99c511d-dd29-4831-b72a-d6bcbddf26a4"}, "volume_fraction": null}