{"absolute_quantity": null, "file_links": [], "labels": [], "mass_fraction": null, "material": {"id": "b6aff7fb-3818-4b24-9dfd-d1833d587d67", "scope": "auto", "type": "link_by_uid"}, "name": "Raw Material", "notes": null, "number_fraction": null, "process": {"id": "487084a5-e533-4039-91f0-22f4220638a7", "scope": "auto", "type": "link_by_uid"}, "spec": {"id": "1f4bc9cf-5fde-47e1-a88c-4902875701de", "scope": "auto", "type": "link_by_uid"}, "tags": [], "type": "ingredient_run", "uids": {"auto": "2cd19648-5512-4956-8e56-45264baa986e"}, "volume_fraction": null}