{"absolute_quantity": null, "file_links": [], "labels": [], "mass_fraction": null, "material": {"id": "fccabb58-dc1e-4a9a-907f-23d8462eba7d", "scope": "auto", "type": "link_by_uid"}, "name": "Sample", "notes": null, "number_fraction": null, "process": {"id": "b04d2967-406c-4fa5-b15b-f206e899353e", "scope": "auto", "type": "link_by_uid"}, "spec": {"id": "e3048ad4-8c99-4ba4-8f20-e6907fa9af8a", "scope": "auto", "type": "link_by_uid"}, "tags": [], "type": "ingredient_run", "uids": {"auto": "115f762c-4023-4259-83e0-ced044677687"}, "volume_fraction": null}