{"absolute_quantity": null, "file_links": [], "labels": [], "mass_fraction": null, "material": {"id": "1a4f841f-cce4-4c5b-830f-07c686ffe100", "scope": "auto", "type": "link_by_uid"}, "name": "Impact Sample", "notes": null, "number_fraction": null, "process": {"id": "2f8f9411-d9f3-4a52-9f87-5a72eb181dc5", "scope": "auto", "type": "link_by_uid"}, "spec": {"id": "44536135-a3a2-4d33-9e42-adcb3a7b8204", "scope": "auto", "type": "link_by_uid"}, "tags": [], "type": "ingredient_run", "uids": {"auto": "77b281d6-ce5e-493d-b940-24b6a7428165"}, "volume_fraction": null}