{"absolute_quantity": null, "file_links": [], "labels": [], "mass_fraction": null, "material": {"id": "2e1ebfa5-ca8c-42e0-801a-15b62e6948eb", "scope": "auto", "type": "link_by_uid"}, "name": "Chosen Flyer", "notes": null, "number_fraction": null, "process": {"id": "75a6bea7-6da0-411e-a0d4-ed6b2a84ce67", "scope": "auto", "type": "link_by_uid"}, "spec": {"id": "e6223eae-51d4-426c-b10b-1ab55849d4d3", "scope": "auto", "type": "link_by_uid"}, "tags": [], "type": "ingredient_run", "uids": {"auto": "b7f3743a-f5c8-4b5f-830e-f92c8b4e339f"}, "volume_fraction": null}