{"absolute_quantity": null, "file_links": [], "labels": [], "mass_fraction": null, "material": {"id": "2a845e80-42ce-432f-9fae-a94276cc41dc", "scope": "auto", "type": "link_by_uid"}, "name": "Flyer and Spacer", "notes": null, "number_fraction": null, "process": {"id": "21286531-4dbc-401a-b674-49145661a054", "scope": "auto", "type": "link_by_uid"}, "spec": {"id": "b8875f80-cc5d-414c-a6f3-17cd3645483c", "scope": "auto", "type": "link_by_uid"}, "tags": [], "type": "ingredient_run", "uids": {"auto": "d15b99d2-92b2-4aeb-b026-326a7bc74d66"}, "volume_fraction": null}