{"absolute_quantity": null, "file_links": [], "labels": [], "mass_fraction": null, "material": {"id": "1877a372-ae1a-4df3-8543-15dbda27b771", "scope": "auto", "type": "link_by_uid"}, "name": "Impact Sample", "notes": null, "number_fraction": null, "process": {"id": "370f4a34-f2ea-498e-8eb7-eb5089bb4e1a", "scope": "auto", "type": "link_by_uid"}, "spec": {"id": "44536135-a3a2-4d33-9e42-adcb3a7b8204", "scope": "auto", "type": "link_by_uid"}, "tags": [], "type": "ingredient_run", "uids": {"auto": "7e57868a-0c0e-4c88-aec6-172b32d6961f"}, "volume_fraction": null}