{"absolute_quantity": null, "file_links": [], "labels": [], "mass_fraction": null, "material": {"id": "af1759ad-3108-44f6-b0aa-08990baddd81", "scope": "auto", "type": "link_by_uid"}, "name": "Chosen Flyer", "notes": null, "number_fraction": null, "process": {"id": "ecc19bb2-040b-404b-8c23-33f03674f664", "scope": "auto", "type": "link_by_uid"}, "spec": {"id": "0ded66f7-777a-4713-a70d-16e08af53266", "scope": "auto", "type": "link_by_uid"}, "tags": [], "type": "ingredient_run", "uids": {"auto": "3bbc69e8-66f9-4ec8-b3b7-be694edfaf24"}, "volume_fraction": null}