{"absolute_quantity": null, "file_links": [], "labels": [], "mass_fraction": null, "material": {"id": "04d8efa1-d3a9-4ff2-b0a3-fbf21bad8b66", "scope": "auto", "type": "link_by_uid"}, "name": "Spacer Material", "notes": null, "number_fraction": null, "process": {"id": "14cded37-9999-4617-8b7c-783d17b76bd2", "scope": "auto", "type": "link_by_uid"}, "spec": {"id": "a6aeb3e4-f2cc-4d36-a3f9-82262f43a9f3", "scope": "auto", "type": "link_by_uid"}, "tags": [], "type": "ingredient_run", "uids": {"auto": "cb6b5b10-c1b1-4fb8-9e79-6799a8175f3a"}, "volume_fraction": null}