{"absolute_quantity": null, "file_links": [], "labels": [], "mass_fraction": null, "material": {"id": "bb534d82-bde0-46a4-ba13-34596bc3ed40", "scope": "auto", "type": "link_by_uid"}, "name": "Chosen Flyer", "notes": null, "number_fraction": null, "process": {"id": "b5c5cac9-fd07-4f8e-a622-62778b217076", "scope": "auto", "type": "link_by_uid"}, "spec": {"id": "e6223eae-51d4-426c-b10b-1ab55849d4d3", "scope": "auto", "type": "link_by_uid"}, "tags": [], "type": "ingredient_run", "uids": {"auto": "10eae76e-519c-4f48-bca7-b344c6b96a37"}, "volume_fraction": null}