{"absolute_quantity": null, "file_links": [], "labels": [], "mass_fraction": null, "material": {"id": "e33f62b1-0bb8-4208-aca1-fb4f5b526f46", "scope": "auto", "type": "link_by_uid"}, "name": "Chosen Flyer", "notes": null, "number_fraction": null, "process": {"id": "71fd42db-12c5-4827-b050-f985b4a14914", "scope": "auto", "type": "link_by_uid"}, "spec": {"id": "e6223eae-51d4-426c-b10b-1ab55849d4d3", "scope": "auto", "type": "link_by_uid"}, "tags": [], "type": "ingredient_run", "uids": {"auto": "b10fd247-c9d7-44b1-8765-785d54aee01d"}, "volume_fraction": null}