{"absolute_quantity": null, "file_links": [], "labels": [], "mass_fraction": null, "material": {"id": "bad7562e-b9a2-420d-9cd2-0fda983a30cf", "scope": "auto", "type": "link_by_uid"}, "name": "Flyer and Spacer", "notes": null, "number_fraction": null, "process": {"id": "e6a5606e-b51e-4e55-994d-b89bb597ef84", "scope": "auto", "type": "link_by_uid"}, "spec": {"id": "3063b977-7d62-4c56-a862-d2daf37adbdd", "scope": "auto", "type": "link_by_uid"}, "tags": [], "type": "ingredient_run", "uids": {"auto": "99aa4b31-866b-40ab-82bf-db72d12a6fc0"}, "volume_fraction": null}