{"absolute_quantity": null, "file_links": [], "labels": [], "mass_fraction": null, "material": {"id": "493cc760-12b2-4d02-91db-741a400e86df", "scope": "auto", "type": "link_by_uid"}, "name": "Chosen Flyer", "notes": null, "number_fraction": null, "process": {"id": "72cc6718-40a0-4357-a01f-d04785c74b1c", "scope": "auto", "type": "link_by_uid"}, "spec": {"id": "e6223eae-51d4-426c-b10b-1ab55849d4d3", "scope": "auto", "type": "link_by_uid"}, "tags": [], "type": "ingredient_run", "uids": {"auto": "24cda184-ddbf-4f47-bb51-244ea09ce043"}, "volume_fraction": null}