{"absolute_quantity": null, "file_links": [], "labels": [], "mass_fraction": null, "material": {"id": "e17b3b83-20b7-4458-990a-883f860196d3", "scope": "auto", "type": "link_by_uid"}, "name": "Flyer and Spacer", "notes": null, "number_fraction": null, "process": {"id": "bf4f36f7-61b9-4b40-ac8b-77f260ad6e5f", "scope": "auto", "type": "link_by_uid"}, "spec": {"id": "b8875f80-cc5d-414c-a6f3-17cd3645483c", "scope": "auto", "type": "link_by_uid"}, "tags": [], "type": "ingredient_run", "uids": {"auto": "72195036-72ff-458f-98d4-694d056b2ecd"}, "volume_fraction": null}