{"absolute_quantity": null, "file_links": [], "labels": [], "mass_fraction": null, "material": {"id": "0106d5c0-84ff-456d-b514-d740d9ce0acb", "scope": "auto", "type": "link_by_uid"}, "name": "Spacer Material", "notes": null, "number_fraction": null, "process": {"id": "07df7206-f663-4eb0-9df2-4e4f76cc9f22", "scope": "auto", "type": "link_by_uid"}, "spec": {"id": "d04ca5d5-15e7-417f-b8d7-34eabd413dc5", "scope": "auto", "type": "link_by_uid"}, "tags": [], "type": "ingredient_run", "uids": {"auto": "ea3d6794-6b02-438d-94d7-bdac366193d7"}, "volume_fraction": null}