{"absolute_quantity": null, "file_links": [], "labels": [], "mass_fraction": null, "material": {"id": "84f41e0d-0e61-4d75-8d05-374d76b75289", "scope": "auto", "type": "link_by_uid"}, "name": "Impact Sample", "notes": null, "number_fraction": null, "process": {"id": "57675cee-1c67-4c8a-ac00-1d30409074e6", "scope": "auto", "type": "link_by_uid"}, "spec": {"id": "8bbe9721-9c08-44a8-b304-fad1cad139c5", "scope": "auto", "type": "link_by_uid"}, "tags": [], "type": "ingredient_run", "uids": {"auto": "7bfb52a0-5dad-4df0-9e78-6bdbf74e9f6c"}, "volume_fraction": null}