{"absolute_quantity": null, "file_links": [], "labels": [], "mass_fraction": null, "material": {"id": "0c4f802d-f545-44bb-9a8a-2578e50b1db5", "scope": "auto", "type": "link_by_uid"}, "name": "Flyer and Spacer", "notes": null, "number_fraction": null, "process": {"id": "ecc949c0-5015-457c-8a19-bde979a13b6a", "scope": "auto", "type": "link_by_uid"}, "spec": {"id": "23a1d49a-cd56-4f1c-af0c-75999c9e0c21", "scope": "auto", "type": "link_by_uid"}, "tags": [], "type": "ingredient_run", "uids": {"auto": "86816272-4358-4454-b8d9-f4e8558b4134"}, "volume_fraction": null}