{"absolute_quantity": null, "file_links": [], "labels": [], "mass_fraction": null, "material": {"id": "e714335d-3f3c-4d28-ad8a-2c29696a6b9c", "scope": "auto", "type": "link_by_uid"}, "name": "Flyer Stack", "notes": null, "number_fraction": null, "process": {"id": "4a372a73-cc50-4a05-a132-494956ea475a", "scope": "auto", "type": "link_by_uid"}, "spec": {"id": "95b6f6c6-3520-4685-858a-786c330fdd55", "scope": "auto", "type": "link_by_uid"}, "tags": [], "type": "ingredient_run", "uids": {"auto": "fad37111-bf0b-4d1d-a43d-ba92c7c3a11d"}, "volume_fraction": null}