{"absolute_quantity": null, "file_links": [], "labels": [], "mass_fraction": null, "material": {"id": "fca739b2-68b4-4cac-baec-2278f1dbbf3c", "scope": "auto", "type": "link_by_uid"}, "name": "Impact Sample", "notes": null, "number_fraction": null, "process": {"id": "e25e0eba-8480-4478-8901-793278da5ffb", "scope": "auto", "type": "link_by_uid"}, "spec": {"id": "36208efb-4df7-4d21-8031-d13aa9d9b34c", "scope": "auto", "type": "link_by_uid"}, "tags": [], "type": "ingredient_run", "uids": {"auto": "32fe0d65-82ec-4daf-b7f7-9ab3ad6e0c67"}, "volume_fraction": null}