{"absolute_quantity": null, "file_links": [], "labels": [], "mass_fraction": null, "material": {"id": "ae6c4d94-0ede-47aa-8d81-241ac1677a26", "scope": "auto", "type": "link_by_uid"}, "name": "Flyer Stack", "notes": null, "number_fraction": null, "process": {"id": "96a64f19-2aa0-4fae-a9f9-fadbf003a148", "scope": "auto", "type": "link_by_uid"}, "spec": {"id": "95b6f6c6-3520-4685-858a-786c330fdd55", "scope": "auto", "type": "link_by_uid"}, "tags": [], "type": "ingredient_run", "uids": {"auto": "d4eed9fb-76a4-43a2-97ef-2f3e400dcd22"}, "volume_fraction": null}