{"absolute_quantity": null, "file_links": [], "labels": [], "mass_fraction": null, "material": {"id": "2b921201-6065-460d-900c-bb6b7bed1a36", "scope": "auto", "type": "link_by_uid"}, "name": "Flyer Stack", "notes": null, "number_fraction": null, "process": {"id": "a5a74e3b-1bd7-48d5-8415-3852400a2961", "scope": "auto", "type": "link_by_uid"}, "spec": {"id": "faca228e-f191-4175-99de-f8ca55303044", "scope": "auto", "type": "link_by_uid"}, "tags": [], "type": "ingredient_run", "uids": {"auto": "622585a7-6340-416c-9d4c-9fdf3e0db1cc"}, "volume_fraction": null}