{"absolute_quantity": null, "file_links": [], "labels": [], "mass_fraction": null, "material": {"id": "32d6022b-4b16-47d6-8014-5d8ef92fb183", "scope": "auto", "type": "link_by_uid"}, "name": "Cut Spacer", "notes": null, "number_fraction": null, "process": {"id": "93c3b3f5-e261-4c79-a3c8-a8e8381eab9c", "scope": "auto", "type": "link_by_uid"}, "spec": {"id": "7cefd8eb-20b6-41b0-bcea-f2fc3ab8f7a1", "scope": "auto", "type": "link_by_uid"}, "tags": [], "type": "ingredient_run", "uids": {"auto": "b80c4d16-b65c-4b29-b48b-b3ff65a66bbb"}, "volume_fraction": null}