{"absolute_quantity": null, "file_links": [], "labels": [], "mass_fraction": null, "material": {"id": "cf46c543-f986-4cc0-9ccb-d85b03a2ba5e", "scope": "auto", "type": "link_by_uid"}, "name": "Chosen Flyer", "notes": null, "number_fraction": null, "process": {"id": "31b37130-3536-4651-a6e1-8224f4a5494d", "scope": "auto", "type": "link_by_uid"}, "spec": {"id": "e6223eae-51d4-426c-b10b-1ab55849d4d3", "scope": "auto", "type": "link_by_uid"}, "tags": [], "type": "ingredient_run", "uids": {"auto": "429d3c2d-e0f9-41ae-9316-a498308656fb"}, "volume_fraction": null}