{"absolute_quantity": null, "file_links": [], "labels": [], "mass_fraction": null, "material": {"id": "078c12bc-3b08-488b-8748-91ecc8176f80", "scope": "auto", "type": "link_by_uid"}, "name": "Cut Spacer", "notes": null, "number_fraction": null, "process": {"id": "ee864a7d-1d30-4f8b-b8e6-c92361b3cb75", "scope": "auto", "type": "link_by_uid"}, "spec": {"id": "7cefd8eb-20b6-41b0-bcea-f2fc3ab8f7a1", "scope": "auto", "type": "link_by_uid"}, "tags": [], "type": "ingredient_run", "uids": {"auto": "46bffe8d-b3e9-4070-8e28-09c0f4e00da7"}, "volume_fraction": null}