{"conditions": [], "file_links": [], "material": {"id": "c733f7ea-4e4a-4332-b5b4-cd853d064d2b", "scope": "auto", "type": "link_by_uid"}, "name": "SpacerOuterDiameter", "notes": null, "parameters": [], "properties": [{"file_links": [], "name": "SpacerOuterDiameter", "notes": null, "origin": "measured", "template": {"id": "ddc6deb1-7024-40c9-8aed-4f51c277157d", "scope": "auto", "type": "link_by_uid"}, "type": "property", "value": {"nominal": 3.2, "type": "nominal_real", "units": "millimeter"}}], "source": {"performed_by": "Diamond", "performed_date": "02/22/2022", "type": "performed_source"}, "spec": null, "tags": [], "type": "measurement_run", "uids": {"auto": "7c0b4e05-5382-410e-a3bb-80117644b44f"}}