{"conditions": [], "file_links": [], "material": {"id": "2e11d0b4-95bf-49a0-85f8-bb2fe4d8e9fb", "scope": "auto", "type": "link_by_uid"}, "name": "Glasslength", "notes": null, "parameters": [], "properties": [{"file_links": [], "name": "Glasslength", "notes": null, "origin": "measured", "template": {"id": "828c3483-d5ab-4eab-84ce-60ad7e76eed3", "scope": "auto", "type": "link_by_uid"}, "type": "property", "value": {"nominal": 50.82, "type": "nominal_real", "units": "millimeter"}}], "source": {"performed_by": "Zare", "performed_date": "03/18/2023", "type": "performed_source"}, "spec": null, "tags": [], "type": "measurement_run", "uids": {"auto": "4377e5d3-d1da-42b8-a0cd-3844b021e985"}}