{"conditions": [], "file_links": [{"filename": "F2--20230328--00003", "type": "file_link", "url": null}, {"filename": "BP--20230328--00003", "type": "file_link", "url": null}], "material": {"id": "04a15224-7a24-4161-9ce5-302558725e1a", "scope": "auto", "type": "link_by_uid"}, "name": "Flyer velocity analysis", "notes": "", "parameters": [], "properties": [], "source": {"performed_by": "Zare", "performed_date": "03/28/2023", "type": "performed_source"}, "spec": {"id": "ee4d54d9-2e7e-4a16-8443-fd547f479e2c", "scope": "auto", "type": "link_by_uid"}, "tags": ["NewEnergyMeasurement::Yes", "ExperimentDayCounter::00003", "recordId::2052", "modId::5", "ObjectType::LaserShockExperiment"], "type": "measurement_run", "uids": {"auto": "5f7ae874-8c78-4b1c-a3d1-f745f4770210"}}