{"conditions": [], "file_links": [], "material": {"id": "c2e230e8-b196-418e-8f49-524ac05766b1", "scope": "auto", "type": "link_by_uid"}, "name": "SampleThickness", "notes": null, "parameters": [], "properties": [{"file_links": [], "name": "SampleThickness", "notes": null, "origin": "measured", "template": {"id": "ed85ad77-21c6-4f63-910b-505fe1780ed4", "scope": "auto", "type": "link_by_uid"}, "type": "property", "value": {"nominal": 198.0, "type": "nominal_real", "units": "micrometer"}}], "source": {"performed_by": "Diamond", "performed_date": "06/21/2022", "type": "performed_source"}, "spec": null, "tags": [], "type": "measurement_run", "uids": {"auto": "c515ee9a-e9f1-4f3a-8c8e-c9fc8ffda1b3"}}