{"conditions": [], "file_links": [], "material": {"id": "81260324-5df3-4349-a1f5-41e6be8cd8e9", "scope": "auto", "type": "link_by_uid"}, "name": "SampleThickness", "notes": null, "parameters": [], "properties": [{"file_links": [], "name": "SampleThickness", "notes": null, "origin": "measured", "template": {"id": "ed85ad77-21c6-4f63-910b-505fe1780ed4", "scope": "auto", "type": "link_by_uid"}, "type": "property", "value": {"nominal": 205.0, "type": "nominal_real", "units": "micrometer"}}], "source": {"performed_by": "Lezcano", "performed_date": "09/22/2021", "type": "performed_source"}, "spec": null, "tags": [], "type": "measurement_run", "uids": {"auto": "42c3938f-33ed-4119-afc9-8f20f507cfaf"}}