{"conditions": [], "file_links": [], "material": {"id": "c7bb1394-f7e2-4e7c-a7b1-1cb60157406c", "scope": "auto", "type": "link_by_uid"}, "name": "GlassThickness4", "notes": null, "parameters": [], "properties": [{"file_links": [], "name": "GlassThickness4", "notes": null, "origin": "measured", "template": {"id": "9469e68f-0e34-4ba6-857e-d1d6e8f34e75", "scope": "auto", "type": "link_by_uid"}, "type": "property", "value": {"nominal": 6.459, "type": "nominal_real", "units": "millimeter"}}], "source": {"performed_by": "Lim", "performed_date": "07/26/2022", "type": "performed_source"}, "spec": null, "tags": [], "type": "measurement_run", "uids": {"auto": "5d2e1746-2df6-46d9-ab41-da84075a26de"}}