{"conditions": [], "file_links": [], "material": {"id": "aa0a8c6a-8a8f-46ce-a035-90496b792c43", "scope": "auto", "type": "link_by_uid"}, "name": "GlassThickness4", "notes": null, "parameters": [], "properties": [{"file_links": [], "name": "GlassThickness4", "notes": null, "origin": "measured", "template": {"id": "9469e68f-0e34-4ba6-857e-d1d6e8f34e75", "scope": "auto", "type": "link_by_uid"}, "type": "property", "value": {"nominal": 6.47, "type": "nominal_real", "units": "millimeter"}}], "source": {"performed_by": "Zare", "performed_date": "03/18/2023", "type": "performed_source"}, "spec": null, "tags": [], "type": "measurement_run", "uids": {"auto": "e27fdb53-99e5-4b30-898d-192a78deacd5"}}