{"conditions": [], "file_links": [], "material": {"id": "96303603-7b84-44bc-a6db-abe70dc34b6a", "scope": "auto", "type": "link_by_uid"}, "name": "SpacerInnerDiameter", "notes": null, "parameters": [], "properties": [{"file_links": [], "name": "SpacerInnerDiameter", "notes": null, "origin": "measured", "template": {"id": "ddc6deb1-7024-40c9-8aed-4f51c277157d", "scope": "auto", "type": "link_by_uid"}, "type": "property", "value": {"nominal": 2.2, "type": "nominal_real", "units": "millimeter"}}], "source": {"performed_by": "Diamond", "performed_date": "11/07/2021", "type": "performed_source"}, "spec": null, "tags": [], "type": "measurement_run", "uids": {"auto": "3505a851-b695-40ba-b1f8-7c5eda9be1c0"}}