{"conditions": [], "file_links": [], "material": {"id": "bd5e8b59-6bf8-4e64-9609-b6056ba55b8f", "scope": "auto", "type": "link_by_uid"}, "name": "SpacerOuterDiameter", "notes": null, "parameters": [], "properties": [{"file_links": [], "name": "SpacerOuterDiameter", "notes": null, "origin": "measured", "template": {"id": "ddc6deb1-7024-40c9-8aed-4f51c277157d", "scope": "auto", "type": "link_by_uid"}, "type": "property", "value": {"nominal": 3.0, "type": "nominal_real", "units": "millimeter"}}], "source": {"performed_by": "Diamond", "performed_date": "01/28/2022", "type": "performed_source"}, "spec": null, "tags": [], "type": "measurement_run", "uids": {"auto": "d22d82ad-faa6-4f7a-8d6f-29915c4bbcfb"}}