{"conditions": [], "file_links": [{"filename": "F2--20211026--00003", "type": "file_link", "url": null}, {"filename": "BP--20211026--00003", "type": "file_link", "url": null}], "material": {"id": "660eca31-f184-4575-a70b-8bce6a27c386", "scope": "auto", "type": "link_by_uid"}, "name": "Spall", "notes": "", "parameters": [], "properties": [{"file_links": [], "name": "MaxVelocity", "notes": null, "origin": "measured", "template": {"id": "00f132e7-60d8-472c-80cc-0aec952f214e", "scope": "auto", "type": "link_by_uid"}, "type": "property", "value": {"nominal": 998.0, "type": "nominal_real", "units": "meter / second"}}, {"file_links": [], "name": "EstImpactVelocity", "notes": null, "origin": "measured", "template": {"id": "b28085f0-c069-4816-9dec-c0f54b47d5ea", "scope": "auto", "type": "link_by_uid"}, "type": "property", "value": {"nominal": 775.25, "type": "nominal_real", "units": "meter / second"}}], "source": {"performed_by": "Lezcano", "performed_date": "10/26/2021", "type": "performed_source"}, "spec": {"id": "8c99b7e7-e4dd-4860-ac22-163005436576", "scope": "auto", "type": "link_by_uid"}, "tags": ["NewEnergyMeasurement::No", "RecoveryBox::2", "RecoveryRow::3", "RecoveryColumn::3", "GrantFunding::MEDE_Metals", "recordId::227", "modId::14", "ObjectType::LaserShockExperiment"], "type": "measurement_run", "uids": {"auto": "e7a02b28-c497-4d49-b431-03e9fe6895ef"}}