{"conditions": [], "file_links": [], "material": {"id": "0aa512c0-174a-43fc-a9a4-4fdaec9efaf5", "scope": "auto", "type": "link_by_uid"}, "name": "GlassThickness1", "notes": null, "parameters": [], "properties": [{"file_links": [], "name": "GlassThickness1", "notes": null, "origin": "measured", "template": {"id": "9469e68f-0e34-4ba6-857e-d1d6e8f34e75", "scope": "auto", "type": "link_by_uid"}, "type": "property", "value": {"nominal": 6.498, "type": "nominal_real", "units": "millimeter"}}], "source": {"performed_by": "Diamond", "performed_date": "07/20/2022", "type": "performed_source"}, "spec": null, "tags": [], "type": "measurement_run", "uids": {"auto": "922c309b-9d02-4f77-8b05-1c2a63444bc5"}}