{"conditions": [], "file_links": [{"filename": "F2--20220624--00116", "type": "file_link", "url": null}, {"filename": "BP--20220624--00116", "type": "file_link", "url": null}], "material": {"id": "49cd7fdb-9484-4bf9-822e-05abb5128196", "scope": "auto", "type": "link_by_uid"}, "name": "Spall", "notes": "", "parameters": [], "properties": [{"file_links": [], "name": "EstImpactVelocity", "notes": null, "origin": "measured", "template": {"id": "b28085f0-c069-4816-9dec-c0f54b47d5ea", "scope": "auto", "type": "link_by_uid"}, "type": "property", "value": {"nominal": 525.0, "type": "nominal_real", "units": "meter / second"}}], "source": {"performed_by": "Diamond", "performed_date": "06/24/2022", "type": "performed_source"}, "spec": {"id": "de94b348-b8b3-475f-9a9b-b2748529645f", "scope": "auto", "type": "link_by_uid"}, "tags": ["NewEnergyMeasurement::No", "ExperimentDayCounter::00116", "recordId::1454", "modId::0", "ObjectType::LaserShockExperiment"], "type": "measurement_run", "uids": {"auto": "99f6fd3a-d89b-4846-9426-a0b5b94bde09"}}