{"conditions": [], "file_links": [{"filename": "F2--20220624--00030", "type": "file_link", "url": null}, {"filename": "BP--20220624--00030", "type": "file_link", "url": null}], "material": {"id": "f149976d-c956-4830-904b-9c3a3d5a2229", "scope": "auto", "type": "link_by_uid"}, "name": "Flyer velocity analysis", "notes": "", "parameters": [], "properties": [{"file_links": [], "name": "EstImpactVelocity", "notes": null, "origin": "measured", "template": {"id": "b28085f0-c069-4816-9dec-c0f54b47d5ea", "scope": "auto", "type": "link_by_uid"}, "type": "property", "value": {"nominal": 300.0, "type": "nominal_real", "units": "meter / second"}}], "source": {"performed_by": "Diamond", "performed_date": "06/24/2022", "type": "performed_source"}, "spec": {"id": "7aaf044e-96e7-4bd6-8911-7d8a912b2dd9", "scope": "auto", "type": "link_by_uid"}, "tags": ["NewEnergyMeasurement::No", "ExperimentDayCounter::00030", "recordId::1368", "modId::0", "ObjectType::LaserShockExperiment"], "type": "measurement_run", "uids": {"auto": "6fa13df0-c1c5-4e60-a622-b31275ea985d"}}