{"conditions": [], "file_links": [], "material": {"id": "fe23c64d-b578-4ecb-a5ea-3670fef4a3ce", "scope": "auto", "type": "link_by_uid"}, "name": "GlassThickness3", "notes": null, "parameters": [], "properties": [{"file_links": [], "name": "GlassThickness3", "notes": null, "origin": "measured", "template": {"id": "9469e68f-0e34-4ba6-857e-d1d6e8f34e75", "scope": "auto", "type": "link_by_uid"}, "type": "property", "value": {"nominal": 6.492, "type": "nominal_real", "units": "millimeter"}}], "source": {"performed_by": "DiMarco", "performed_date": "01/27/2022", "type": "performed_source"}, "spec": null, "tags": [], "type": "measurement_run", "uids": {"auto": "b526c839-cd0c-48c8-b422-c3dcb868531e"}}