{"conditions": [], "file_links": [], "material": {"id": "dc39b549-3cf3-4853-869b-1d4fc9d76a52", "scope": "auto", "type": "link_by_uid"}, "name": "SampleThickness", "notes": null, "parameters": [], "properties": [{"file_links": [], "name": "SampleThickness", "notes": null, "origin": "measured", "template": {"id": "ed85ad77-21c6-4f63-910b-505fe1780ed4", "scope": "auto", "type": "link_by_uid"}, "type": "property", "value": {"nominal": 197.0, "type": "nominal_real", "units": "micrometer"}}], "source": {"performed_by": "DiMarco", "performed_date": "03/17/2022", "type": "performed_source"}, "spec": null, "tags": [], "type": "measurement_run", "uids": {"auto": "d4cf51ae-63a7-477c-ba32-5d8032622e5a"}}