{"conditions": [], "file_links": [], "material": {"id": "1148f765-6453-482d-a600-e9129e0ac140", "scope": "auto", "type": "link_by_uid"}, "name": "SpacerInnerDiameter", "notes": null, "parameters": [], "properties": [{"file_links": [], "name": "SpacerInnerDiameter", "notes": null, "origin": "measured", "template": {"id": "ddc6deb1-7024-40c9-8aed-4f51c277157d", "scope": "auto", "type": "link_by_uid"}, "type": "property", "value": {"nominal": 2.2, "type": "nominal_real", "units": "millimeter"}}], "source": {"performed_by": "Diamond", "performed_date": "11/06/2021", "type": "performed_source"}, "spec": null, "tags": [], "type": "measurement_run", "uids": {"auto": "052f296d-3d63-4a46-9ff1-c1d751506318"}}