{"conditions": [], "file_links": [{"filename": "13_31_13", "type": "file_link", "url": null}, {"filename": "F2--20220923--00018", "type": "file_link", "url": null}, {"filename": "BP--20220923--00018", "type": "file_link", "url": null}], "material": {"id": "fe285410-0c4c-4284-8220-4bf2bba6bf00", "scope": "auto", "type": "link_by_uid"}, "name": "Spall", "notes": "looks like reflective film is spalling off the kapton", "parameters": [], "properties": [{"file_links": [], "name": "EstImpactVelocity", "notes": null, "origin": "measured", "template": {"id": "b28085f0-c069-4816-9dec-c0f54b47d5ea", "scope": "auto", "type": "link_by_uid"}, "type": "property", "value": {"nominal": 493.0, "type": "nominal_real", "units": "meter / second"}}], "source": {"performed_by": "Diamond", "performed_date": "09/23/2022", "type": "performed_source"}, "spec": {"id": "d0c2a7c7-ffe5-48a4-b601-4df594bc4358", "scope": "auto", "type": "link_by_uid"}, "tags": ["NewEnergyMeasurement::No", "ExperimentDayCounter::00018", "recordId::1852", "modId::1", "ObjectType::LaserShockExperiment"], "type": "measurement_run", "uids": {"auto": "5f9ae407-2997-4dbf-a544-2ffbfc2e35ef"}}