{"conditions": [], "file_links": [], "material": {"id": "d8d0aaa4-9230-487f-a606-3483c91a7d54", "scope": "auto", "type": "link_by_uid"}, "name": "GlassThickness3", "notes": null, "parameters": [], "properties": [{"file_links": [], "name": "GlassThickness3", "notes": null, "origin": "measured", "template": {"id": "9469e68f-0e34-4ba6-857e-d1d6e8f34e75", "scope": "auto", "type": "link_by_uid"}, "type": "property", "value": {"nominal": 6.447, "type": "nominal_real", "units": "millimeter"}}], "source": {"performed_by": "DiMarco", "performed_date": "09/27/2021", "type": "performed_source"}, "spec": null, "tags": [], "type": "measurement_run", "uids": {"auto": "3b376304-caa1-4a0c-b8d2-f066d0607dba"}}