{"conditions": [], "file_links": [], "material": {"id": "fe1576ba-6f0c-45bc-876f-c968a0d645da", "scope": "auto", "type": "link_by_uid"}, "name": "SampleThickness", "notes": null, "parameters": [], "properties": [{"file_links": [], "name": "SampleThickness", "notes": null, "origin": "measured", "template": {"id": "ed85ad77-21c6-4f63-910b-505fe1780ed4", "scope": "auto", "type": "link_by_uid"}, "type": "property", "value": {"nominal": 200.0, "type": "nominal_real", "units": "micrometer"}}], "source": {"performed_by": "Lim", "performed_date": "06/10/2022", "type": "performed_source"}, "spec": null, "tags": [], "type": "measurement_run", "uids": {"auto": "3b597f64-8bb8-4eef-aaa5-eeb943f61f3e"}}