{"conditions": [], "file_links": [], "material": {"id": "e66a9570-9310-416b-8b2b-25f0d846afff", "scope": "auto", "type": "link_by_uid"}, "name": "SpacerOuterDiameter", "notes": null, "parameters": [], "properties": [{"file_links": [], "name": "SpacerOuterDiameter", "notes": null, "origin": "measured", "template": {"id": "ddc6deb1-7024-40c9-8aed-4f51c277157d", "scope": "auto", "type": "link_by_uid"}, "type": "property", "value": {"nominal": 3.0, "type": "nominal_real", "units": "millimeter"}}], "source": {"performed_by": "Lezcano", "performed_date": "12/14/2021", "type": "performed_source"}, "spec": null, "tags": [], "type": "measurement_run", "uids": {"auto": "b91974ea-e369-4ce0-8919-1b126152f1a2"}}