{"conditions": [], "file_links": [], "material": {"id": "7d4f7f26-b4c7-4095-bd0c-e73cc839e867", "scope": "auto", "type": "link_by_uid"}, "name": "SampleDiameter", "notes": null, "parameters": [], "properties": [{"file_links": [], "name": "SampleDiameter", "notes": null, "origin": "measured", "template": {"id": "76884662-f071-4c42-ab8d-539774bbbc73", "scope": "auto", "type": "link_by_uid"}, "type": "property", "value": {"nominal": 3.0, "type": "nominal_real", "units": "millimeter"}}], "source": {"performed_by": "Lim", "performed_date": "06/10/2022", "type": "performed_source"}, "spec": null, "tags": [], "type": "measurement_run", "uids": {"auto": "7f08aa8c-9fd4-449f-b74a-ca92bf41e3e0"}}