{"conditions": [], "file_links": [], "name": "Purchasing Spacer", "notes": null, "parameters": [{"file_links": [], "name": "SpacerSupplier", "notes": null, "origin": "specified", "template": {"id": "e3a2d3b7-db9f-4adb-a469-6b694c53340f", "scope": "auto", "type": "link_by_uid"}, "type": "parameter", "value": {"category": "CS Hyde", "type": "nominal_categorical"}}], "tags": [], "template": {"id": "d5557c35-5104-4480-8a46-f093f8e8a4bb", "scope": "auto", "type": "link_by_uid"}, "type": "process_spec", "uids": {"auto": "d6d849c4-5a00-4176-8b7c-0e0ac276e32e"}}